LICENSE.txt
README.md
setup.cfg
setup.py
DBLite3/__init__.py
DBLite3/_alter.py
DBLite3/_create.py
DBLite3/_delete.py
DBLite3/_drop.py
DBLite3/_exceptions.py
DBLite3/_funcs.py
DBLite3/_insert.py
DBLite3/_select.py
DBLite3/_update.py
DBLite3.egg-info/PKG-INFO
DBLite3.egg-info/SOURCES.txt
DBLite3.egg-info/dependency_links.txt
DBLite3.egg-info/top_level.txt
tests/test_1_create.py
tests/test_2_insert.py
tests/test_3_update.py
tests/test_4_alter.py
tests/test_5_select.py
tests/test_6_delete.py
tests/test_7_drop.py
tests/test_8_funcs.py