Metadata-Version: 2.1
Name: DBLite3
Version: 0.2.0
Summary: NoSQL database
Home-page: https://github.com/macht1212/LiteDB/
Download-URL: https://github.com/macht1212/DBLite3/dist/DBLite3-0.2.0.tar.gz
Author: Alexander Nazimov
Author-email: nasimov.alexander@gmail.com
License: MIT license
Keywords: database,nosql,litedb,json
Classifier: Intended Audience :: Developers
Classifier: Natural Language :: English
Classifier: License :: OSI Approved :: MIT License
Classifier: Operating System :: OS Independent
Classifier: Programming Language :: Python
Classifier: Programming Language :: Python :: 3
Classifier: Programming Language :: Python :: 3.9
Classifier: Programming Language :: Python :: 3.10
Classifier: Programming Language :: Python :: 3.11
Classifier: Programming Language :: Python :: 3 :: Only
Classifier: Programming Language :: Python :: Implementation :: PyPy
Classifier: Programming Language :: Python :: Implementation :: CPython
Requires-Python: >=3.9
License-File: LICENSE.txt
